vocabulous/__init__.py
vocabulous/vocabulous.py
vocabulous-0.1.3.dist-info/METADATA
vocabulous-0.1.3.dist-info/WHEEL
vocabulous-0.1.3.dist-info/licenses/LICENSE
vocabulous-0.1.3.dist-info/RECORD
