Metadata-Version: 2.4
Name: vocabulous
Version: 0.1.3
Summary: A bootstrapping language detection system that builds dictionaries from noisy and ambiguous training data
Project-URL: Homepage, https://github.com/omarkamali/vocabulous
Project-URL: Repository, https://github.com/omarkamali/vocabulous.git
Project-URL: Documentation, https://github.com/omarkamali/vocabulous#readme
Project-URL: Bug Tracker, https://github.com/omarkamali/vocabulous/issues
Author-email: Omar Kamali <vocabulous@omarkama.li>
License: MIT
License-File: LICENSE
Keywords: bootstrapping,dictionary-building,language-detection,machine-learning,nlp,text-classification
Classifier: Development Status :: 4 - Beta
Classifier: Intended Audience :: Developers
Classifier: Intended Audience :: Science/Research
Classifier: License :: OSI Approved :: MIT License
Classifier: Operating System :: OS Independent
Classifier: Programming Language :: Python :: 3
Classifier: Programming Language :: Python :: 3.8
Classifier: Programming Language :: Python :: 3.9
Classifier: Programming Language :: Python :: 3.10
Classifier: Programming Language :: Python :: 3.11
Classifier: Programming Language :: Python :: 3.12
Classifier: Topic :: Scientific/Engineering :: Artificial Intelligence
Classifier: Topic :: Text Processing :: Linguistic
Requires-Python: >=3.8
Requires-Dist: datasets>=2.0.0
Requires-Dist: duckdb>=0.8.0
Requires-Dist: huggingface-hub>=0.16.0
Requires-Dist: nltk>=3.6
Requires-Dist: pandas>=1.3.0
Requires-Dist: pyarrow>=12.0.0
Requires-Dist: requests>=2.28.0
Requires-Dist: swifter>=1.0.0
Requires-Dist: tqdm>=4.60.0
Requires-Dist: unscript>=0.0.1
Provides-Extra: dev
Requires-Dist: black>=21.0; extra == 'dev'
Requires-Dist: flake8>=3.8; extra == 'dev'
Requires-Dist: mypy>=0.910; extra == 'dev'
Requires-Dist: pytest-cov>=2.0; extra == 'dev'
Requires-Dist: pytest>=6.0; extra == 'dev'
Provides-Extra: notebooks
Requires-Dist: jupyter>=1.0.0; extra == 'notebooks'
Requires-Dist: matplotlib>=3.3.0; extra == 'notebooks'
Requires-Dist: scikit-learn>=1.0.0; extra == 'notebooks'
Requires-Dist: seaborn>=0.11.0; extra == 'notebooks'
